tensor2robot/.git
tensor2robot/.gitignore
tensor2robot/.pytest_cache/.gitignore
tensor2robot/.pytest_cache/CACHEDIR.TAG
tensor2robot/.pytest_cache/README.md
tensor2robot/.pytest_cache/v/cache/lastfailed
tensor2robot/.pytest_cache/v/cache/nodeids
tensor2robot/.pytest_cache/v/cache/stepwise
tensor2robot/CONTRIBUTING.md
tensor2robot/LICENSE
tensor2robot/README.md
tensor2robot/__init__.py
tensor2robot/bin/run_collect_eval.py
tensor2robot/bin/run_t2r_trainer.py
tensor2robot/export_generators/__init__.py
tensor2robot/export_generators/abstract_export_generator.py
tensor2robot/export_generators/abstract_export_generator_test.py
tensor2robot/export_generators/default_export_generator.py
tensor2robot/export_generators/default_export_generator_test.py
tensor2robot/hooks/__init__.py
tensor2robot/hooks/async_export_hook_builder.py
tensor2robot/hooks/async_export_hook_builder_test.py
tensor2robot/hooks/async_export_hook_builder_tpu_test.py
tensor2robot/hooks/checkpoint_hooks.py
tensor2robot/hooks/checkpoint_hooks_test.py
tensor2robot/hooks/gin_config_hook_builder.py
tensor2robot/hooks/golden_values_hook_builder.py
tensor2robot/hooks/hook_builder.py
tensor2robot/hooks/td3.py
tensor2robot/hooks/td3_test.py
tensor2robot/hooks/variable_logger_hook.py
tensor2robot/input_generators/__init__.py
tensor2robot/input_generators/abstract_input_generator.py
tensor2robot/input_generators/abstract_input_generator_test.py
tensor2robot/input_generators/default_input_generator.py
tensor2robot/input_generators/default_input_generator_test.py
tensor2robot/layers/__init__.py
tensor2robot/layers/bcz_networks.py
tensor2robot/layers/film_resnet_model.py
tensor2robot/layers/mdn.py
tensor2robot/layers/mdn_test.py
tensor2robot/layers/resnet.py
tensor2robot/layers/resnet_test.py
tensor2robot/layers/snail.py
tensor2robot/layers/snail_test.py
tensor2robot/layers/spatial_softmax.py
tensor2robot/layers/spatial_softmax_test.py
tensor2robot/layers/tec.py
tensor2robot/layers/tec_test.py
tensor2robot-0.1.2.dist-info/METADATA
tensor2robot-0.1.2.dist-info/WHEEL
tensor2robot-0.1.2.dist-info/RECORD
