Metadata-Version: 2.1
Name: tensor2robot
Version: 0.1.2
Summary: Fork of tensor2robot that works with tensorflow 2.15.0 and TF-Agents. Breaking changes will not be introduced without a major version bump and deprecation period.
License: MIT
Author: Sebastian Peralta
Requires-Python: >=3.9,<3.12
Classifier: License :: OSI Approved :: MIT License
Classifier: Programming Language :: Python :: 3
Classifier: Programming Language :: Python :: 3.9
Classifier: Programming Language :: Python :: 3.10
Classifier: Programming Language :: Python :: 3.11
Requires-Dist: absl-py (==2.0.0)
Requires-Dist: astunparse (==1.6.3)
Requires-Dist: cachetools (==5.3.2)
Requires-Dist: certifi (==2023.11.17)
Requires-Dist: charset-normalizer (==3.3.2)
Requires-Dist: flatbuffers (==23.5.26)
Requires-Dist: gast (==0.5.4)
Requires-Dist: gin (==0.1.6)
Requires-Dist: gin-config (==0.5.0)
Requires-Dist: google-auth (==2.25.2)
Requires-Dist: google-auth-oauthlib (==1.2.0)
Requires-Dist: google-pasta (==0.2.0)
Requires-Dist: grpcio (==1.60.0)
Requires-Dist: h5py (==3.10.0)
Requires-Dist: idna (==3.6)
Requires-Dist: iniconfig (==2.0.0)
Requires-Dist: keras (==2.15.0)
Requires-Dist: libclang (==16.0.6)
Requires-Dist: markdown (==3.5.1)
Requires-Dist: markupsafe (==2.1.3)
Requires-Dist: ml-dtypes (==0.2.0)
Requires-Dist: numpy (==1.26.2)
Requires-Dist: oauthlib (==3.2.2)
Requires-Dist: opt-einsum (==3.3.0)
Requires-Dist: packaging (==23.2)
Requires-Dist: pillow (==10.1.0)
Requires-Dist: pluggy (==1.3.0)
Requires-Dist: protobuf (==4.23.4)
Requires-Dist: pyasn1 (==0.5.1)
Requires-Dist: pyasn1-modules (==0.3.0)
Requires-Dist: pytest (==7.4.3)
Requires-Dist: requests (==2.31.0)
Requires-Dist: requests-oauthlib (==1.3.1)
Requires-Dist: rsa (==4.9)
Requires-Dist: six (==1.16.0)
Requires-Dist: tensorboard (==2.15.1)
Requires-Dist: tensorboard-data-server (==0.7.2)
Requires-Dist: tensorflow (==2.15.0)
Requires-Dist: tensorflow-estimator (==2.15.0)
Requires-Dist: tensorflow-io-gcs-filesystem (==0.34.0)
Requires-Dist: tensorflow-macos (==2.15.0)
Requires-Dist: termcolor (==2.4.0)
Requires-Dist: typing-extensions (==4.5.0)
Requires-Dist: urllib3 (==2.1.0)
Requires-Dist: werkzeug (==3.0.1)
Requires-Dist: wrapt (==1.14.1)
